CEFCIG/__init__.py
CEFCIG/_version.py
CEFCIG/cli.py
CEFCIG-1.0.1.data/scripts/CEFCIG
CEFCIG-1.0.1.dist-info/DESCRIPTION.rst
CEFCIG-1.0.1.dist-info/METADATA
CEFCIG-1.0.1.dist-info/RECORD
CEFCIG-1.0.1.dist-info/WHEEL
CEFCIG-1.0.1.dist-info/metadata.json
CEFCIG-1.0.1.dist-info/top_level.txt
tests/__init__.py
tests/test_CEFCIG.py
